{
  "index": {
    "type": "document-heading",
    "description": "",
    "examples": [{
      "title": "Standard",
      "description": "",
      "data": {
        "image": "./document-heading.png",
        "text": "Demander un logement",
        "icons" : [
          {
            "icon": {
              "default": "favorites-outline",
              "hover": "favorites",
              "active": "favorites"
            },
            "url": "#",
            "label": {
              "default": "Ajouter aux favoris",
              "off": "Enlever des favoris"
            }
          },
          {
            "icon": {
              "default": "bell-outline",
              "hover": "bell",
              "active": "bell"
            },
            "url": "#",
            "label": {
              "default": "S'inscrire aux alertes",
              "off": "Se désinscrire des alertes"
            }
          }
        ]
      }
    }, {
      "title": "Icône active",
      "description": "",
      "data": {
        "image": "./document-heading.png",
        "text": "Demander un logement",
        "icons" : [
          {
            "icon": {
              "default": "favorites-outline",
              "hover": "favorites",
              "active": "favorites"
            },
            "url": "#",
            "label": {
              "default": "Ajouter aux favoris",
              "off": "Enlever des favoris"
            }
          },
          {
            "icon": {
              "default": "bell-outline",
              "hover": "bell",
              "active": "bell"
            },
            "url": "#",
            "label": {
              "default": "S'inscrire aux alertes",
              "off": "Se désinscrire des alertes"
            }
          }
        ]
      }
    }, {
      "title": "Test avec titre long",
      "description": "",
      "data": {
        "image": "./document-heading.png",
        "text": "Lorem ipsum dolor sit amet, consectetur adipiscing elit. Nullam egestas porttitor purus vitae volutpat.",
        "icons" : [
          {
            "icon": {
              "default": "favorites-outline",
              "hover": "favorites",
              "active": "favorites"
            },
            "url": "#",
            "label": {
              "default": "Ajouter aux favoris",
              "off": "Enlever des favoris"
            }
          },
          {
            "icon": {
              "default": "bell-outline",
              "hover": "bell",
              "active": "bell"
            },
            "url": "#",
            "label": {
              "default": "S'inscrire aux alertes",
              "off": "Se désinscrire des alertes"
            }
          }
        ]
      }
    }]
  }
}
